{
    "fluentMethods": true,
    "relationships": [
        {
            "relationshipName": "actionObject",
            "otherEntityName": "actionObject",
            "relationshipType": "many-to-one",
            "otherEntityField": "id"
        }
    ],
    "fields": [
        {
            "fieldName": "fieldName",
            "fieldType": "String",
            "fieldValidateRules": [
                "required"
            ]
        }
    ],
    "changelogDate": "20170420163424",
    "dto": "mapstruct",
    "service": "serviceClass",
    "entityTableName": "object_change",
    "pagination": "pager"
}
